timebudget/__init__.py
timebudget/timebudget.py
timebudget-0.7.1.dist-info/LICENSE
timebudget-0.7.1.dist-info/METADATA
timebudget-0.7.1.dist-info/WHEEL
timebudget-0.7.1.dist-info/top_level.txt
timebudget-0.7.1.dist-info/RECORD
