Metadata-Version: 2.1
Name: timebudget
Version: 0.7.1
Summary: Stupidly-simple speed profiling tool for python
Home-page: https://github.com/leopd/timebudget
Author: Leo Dirac
Author-email: leo.dirac@gmail.com
License: Apache-2.0
Keywords: profiling tuning
Platform: UNKNOWN
Classifier: Programming Language :: Python :: 3
Classifier: License :: OSI Approved :: Apache Software License
Classifier: Operating System :: OS Independent
